[
  {
    "node_id": 0,
    "parents": [],
    "claim": "For all integers n > 2, Euler's totient phi(n) is even.",
    "predicate": "n <= 2 or phi(n) % 2 == 0",
    "confidence": 1.0,
    "is_terminal": false,
    "truth": true,
    "truth_reason": "holds"
  },
  {
    "node_id": 1,
    "parents": [
      0
    ],
    "claim": "For all integers n > 2, if n is prime, then phi(n) is even.",
    "predicate": "n <= 2 or not is_prime(n) or phi(n) % 2 == 0",
    "confidence": 1.0,
    "is_terminal": false,
    "truth": true,
    "truth_reason": "holds"
  },
  {
    "node_id": 2,
    "parents": [
      0
    ],
    "claim": "For all integers n > 2, if n is a power of 2, then phi(n) is even.",
    "predicate": "n <= 2 or not (n > 0 and (n & (n - 1)) == 0) or phi(n) % 2 == 0",
    "confidence": 1.0,
    "is_terminal": false,
    "truth": true,
    "truth_reason": "holds"
  },
  {
    "node_id": 3,
    "parents": [
      0,
      1
    ],
    "claim": "For all integers n > 2, if n is a prime power, then phi(n) is even.",
    "predicate": "n <= 2 or not (is_prime(vp(n, 2)) and vp(n, 2) > 0) or phi(n) % 2 == 0",
    "confidence": 0.9,
    "is_terminal": false,
    "truth": true,
    "truth_reason": "holds"
  },
  {
    "node_id": 4,
    "parents": [
      0
    ],
    "claim": "For all integers n > 2, phi(n) is divisible by 2 but not by 4.",
    "predicate": "n <= 2 or phi(n) % 2 == 0 and phi(n) % 4 != 0",
    "confidence": 0.7,
    "is_terminal": false,
    "truth": false,
    "truth_reason": "counterexample"
  },
  {
    "node_id": 5,
    "parents": [
      2
    ],
    "claim": "For all integers n > 2, if n is a power of 2, then phi(n) is a power of 2.",
    "predicate": "n <= 2 or not (n > 0 and (n & (n - 1)) == 0) or (phi(n) & (phi(n) - 1)) == 0",
    "confidence": 0.8,
    "is_terminal": false,
    "truth": true,
    "truth_reason": "holds"
  },
  {
    "node_id": 6,
    "parents": [
      1,
      5
    ],
    "claim": "For all integers n > 2, if n is a prime power of 2, then phi(n) is a power of 2.",
    "predicate": "n <= 2 or not (is_prime(vp(n, 2)) and vp(n, 2) > 0 and (n & (n - 1)) == 0) or (phi(n) & (phi(n) - 1)) == 0",
    "confidence": 0.8,
    "is_terminal": false,
    "truth": true,
    "truth_reason": "holds"
  },
  {
    "node_id": 7,
    "parents": [
      0
    ],
    "claim": "For all integers n > 2, if n is composite, then phi(n) is even.",
    "predicate": "n <= 2 or not (not is_prime(n)) or phi(n) % 2 == 0",
    "confidence": 1.0,
    "is_terminal": false,
    "truth": true,
    "truth_reason": "holds"
  },
  {
    "node_id": 8,
    "parents": [
      7
    ],
    "claim": "For all integers n > 2, if n is a product of two distinct primes, then phi(n) is even.",
    "predicate": "n <= 2 or not (tau(n) == 4 and len([p for p in range(2, n) if is_prime(p) and n % p == 0]) == 2) or phi(n) % 2 == 0",
    "confidence": 1.0,
    "is_terminal": false,
    "truth": true,
    "truth_reason": "holds"
  },
  {
    "node_id": 9,
    "parents": [
      1,
      8
    ],
    "claim": "For all integers n > 2, if n is a product of two distinct primes and one of them is 2, then phi(n) is a multiple of 4.",
    "predicate": "n <= 2 or not (tau(n) == 4 and len([p for p in range(2, n) if is_prime(p) and n % p == 0]) == 2 and 2 in [p for p in range(2, n) if is_prime(p) and n % p == 0]) or phi(n) % 4 == 0",
    "confidence": 0.9,
    "is_terminal": false,
    "truth": false,
    "truth_reason": "counterexample"
  },
  {
    "node_id": 10,
    "parents": [
      0
    ],
    "claim": "For all integers n > 2, if n is a power of an odd prime, then phi(n) is even.",
    "predicate": "n <= 2 or not (is_prime(vp(n, 2)) and vp(n, 2) > 0 and vp(n, 2) % 2 != 0) or phi(n) % 2 == 0",
    "confidence": 1.0,
    "is_terminal": false,
    "truth": true,
    "truth_reason": "holds"
  },
  {
    "node_id": 11,
    "parents": [
      10
    ],
    "claim": "For all integers n > 2, if n is a power of 3, then phi(n) is a multiple of 2 but not 4.",
    "predicate": "n <= 2 or not (vp(n, 3) > 0 and (n & (n - 1)) == 0) or phi(n) % 2 == 0 and phi(n) % 4 != 0",
    "confidence": 0.8,
    "is_terminal": false,
    "truth": true,
    "truth_reason": "holds"
  },
  {
    "node_id": 12,
    "parents": [
      1,
      10
    ],
    "claim": "For all integers n > 2, if n is a power of an odd prime, then phi(n) is a multiple of the prime minus one.",
    "predicate": "n <= 2 or not (is_prime(vp(n, 2)) and vp(n, 2) > 0 and vp(n, 2) % 2 != 0) or phi(n) % (vp(n, 2) - 1) == 0",
    "confidence": 0.9,
    "is_terminal": false,
    "truth": false,
    "truth_reason": "counterexample"
  },
  {
    "node_id": 13,
    "parents": [
      12
    ],
    "claim": "For all integers n > 2, if n is a power of 5, then phi(n) is a multiple of 4.",
    "predicate": "n <= 2 or not (vp(n, 5) > 0 and (n & (n - 1)) == 0) or phi(n) % 4 == 0",
    "confidence": 0.8,
    "is_terminal": false,
    "truth": true,
    "truth_reason": "holds"
  },
  {
    "node_id": 14,
    "parents": [
      0
    ],
    "claim": "For all integers n > 2, if n is a product of two distinct odd primes, then phi(n) is a multiple of 4.",
    "predicate": "n <= 2 or not (tau(n) == 4 and len([p for p in range(2, n) if is_prime(p) and n % p == 0]) == 2 and all(p % 2 != 0 for p in [p for p in range(2, n) if is_prime(p) and n % p == 0])) or phi(n) % 4 == 0",
    "confidence": 0.9,
    "is_terminal": false,
    "truth": true,
    "truth_reason": "holds"
  },
  {
    "node_id": 15,
    "parents": [
      14
    ],
    "claim": "For all integers n > 2, if n is a product of two distinct odd primes and one of them is 3, then phi(n) is a multiple of 4 but not 8.",
    "predicate": "n <= 2 or not (tau(n) == 4 and len([p for p in range(2, n) if is_prime(p) and n % p == 0]) == 2 and all(p % 2 != 0 for p in [p for p in range(2, n) if is_prime(p) and n % p == 0]) and 3 in [p for p in range(2, n) if is_prime(p) and n % p == 0]) or phi(n) % 4 == 0 and phi(n) % 8 != 0",
    "confidence": 0.8,
    "is_terminal": false,
    "truth": false,
    "truth_reason": "counterexample"
  },
  {
    "node_id": 16,
    "parents": [
      0,
      14
    ],
    "claim": "For all integers n > 2, if n is a product of two distinct odd primes and one of them is 5, then phi(n) is a multiple of 8.",
    "predicate": "n <= 2 or not (tau(n) == 4 and len([p for p in range(2, n) if is_prime(p) and n % p == 0]) == 2 and all(p % 2 != 0 for p in [p for p in range(2, n) if is_prime(p) and n % p == 0]) and 5 in [p for p in range(2, n) if is_prime(p) and n % p == 0]) or phi(n) % 8 == 0",
    "confidence": 0.8,
    "is_terminal": false,
    "truth": true,
    "truth_reason": "holds"
  },
  {
    "node_id": 17,
    "parents": [
      0
    ],
    "claim": "For all integers n > 2, if n is a power of 7, then phi(n) is a multiple of 6.",
    "predicate": "n <= 2 or not (vp(n, 7) > 0 and (n & (n - 1)) == 0) or phi(n) % 6 == 0",
    "confidence": 0.8,
    "is_terminal": false,
    "truth": true,
    "truth_reason": "holds"
  },
  {
    "node_id": 18,
    "parents": [
      17
    ],
    "claim": "For all integers n > 2, if n is a power of 7, then phi(n) is a multiple of 6 but not 12.",
    "predicate": "n <= 2 or not (vp(n, 7) > 0 and (n & (n - 1)) == 0) or phi(n) % 6 == 0 and phi(n) % 12 != 0",
    "confidence": 0.7,
    "is_terminal": false,
    "truth": true,
    "truth_reason": "holds"
  },
  {
    "node_id": 19,
    "parents": [
      0,
      17
    ],
    "claim": "For all integers n > 2, if n is a product of 7 and another prime, then phi(n) is a multiple of 6.",
    "predicate": "n <= 2 or not (tau(n) == 4 and 7 in [p for p in range(2, n) if is_prime(p) and n % p == 0]) or phi(n) % 6 == 0",
    "confidence": 0.8,
    "is_terminal": false,
    "truth": true,
    "truth_reason": "holds"
  },
  {
    "node_id": 20,
    "parents": [
      19
    ],
    "claim": "For all integers n > 2, if n is a product of 7 and 3, then phi(n) is a multiple of 6 but not 12.",
    "predicate": "n <= 2 or not (tau(n) == 4 and 7 in [p for p in range(2, n) if is_prime(p) and n % p == 0] and 3 in [p for p in range(2, n) if is_prime(p) and n % p == 0]) or phi(n) % 6 == 0 and phi(n) % 12 != 0",
    "confidence": 0.7,
    "is_terminal": false,
    "truth": false,
    "truth_reason": "counterexample"
  },
  {
    "node_id": 21,
    "parents": [
      0,
      14
    ],
    "claim": "For all integers n > 2, if n is a product of two distinct odd primes, then phi(n) is a multiple of 4 and tau(n) is a multiple of 4.",
    "predicate": "n <= 2 or not (tau(n) == 4 and len([p for p in range(2, n) if is_prime(p) and n % p == 0]) == 2 and all(p % 2 != 0 for p in [p for p in range(2, n) if is_prime(p) and n % p == 0])) or phi(n) % 4 == 0 and tau(n) % 4 == 0",
    "confidence": 0.9,
    "is_terminal": false,
    "truth": true,
    "truth_reason": "holds"
  },
  {
    "node_id": 22,
    "parents": [
      21
    ],
    "claim": "For all integers n > 2, if n is a product of two distinct odd primes and one of them is 3, then phi(n) is a multiple of 4 but not 8 and tau(n) is a multiple of 4.",
    "predicate": "n <= 2 or not (tau(n) == 4 and len([p for p in range(2, n) if is_prime(p) and n % p == 0]) == 2 and all(p % 2 != 0 for p in [p for p in range(2, n) if is_prime(p) and n % p == 0]) and 3 in [p for p in range(2, n) if is_prime(p) and n % p == 0]) or phi(n) % 4 == 0 and phi(n) % 8 != 0 and tau(n) % 4 == 0",
    "confidence": 0.8,
    "is_terminal": false,
    "truth": false,
    "truth_reason": "counterexample"
  },
  {
    "node_id": 23,
    "parents": [
      0,
      21
    ],
    "claim": "For all integers n > 2, if n is a product of two distinct odd primes and one of them is 5, then phi(n) is a multiple of 8 and tau(n) is a multiple of 4.",
    "predicate": "n <= 2 or not (tau(n) == 4 and len([p for p in range(2, n) if is_prime(p) and n % p == 0]) == 2 and all(p % 2 != 0 for p in [p for p in range(2, n) if is_prime(p) and n % p == 0]) and 5 in [p for p in range(2, n) if is_prime(p) and n % p == 0]) or phi(n) % 8 == 0 and tau(n) % 4 == 0",
    "confidence": 0.8,
    "is_terminal": false,
    "truth": true,
    "truth_reason": "holds"
  },
  {
    "node_id": 24,
    "parents": [
      0
    ],
    "claim": "For all integers n > 2, if n is a power of 11, then phi(n) is a multiple of 10.",
    "predicate": "n <= 2 or not (vp(n, 11) > 0 and (n & (n - 1)) == 0) or phi(n) % 10 == 0",
    "confidence": 0.8,
    "is_terminal": false,
    "truth": true,
    "truth_reason": "holds"
  },
  {
    "node_id": 25,
    "parents": [
      24
    ],
    "claim": "For all integers n > 2, if n is a power of 11, then phi(n) is a multiple of 10 but not 20.",
    "predicate": "n <= 2 or not (vp(n, 11) > 0 and (n & (n - 1)) == 0) or phi(n) % 10 == 0 and phi(n) % 20 != 0",
    "confidence": 0.7,
    "is_terminal": false,
    "truth": true,
    "truth_reason": "holds"
  },
  {
    "node_id": 26,
    "parents": [
      0,
      24
    ],
    "claim": "For all integers n > 2, if n is a product of 11 and another prime, then phi(n) is a multiple of 10.",
    "predicate": "n <= 2 or not (tau(n) == 4 and 11 in [p for p in range(2, n) if is_prime(p) and n % p == 0]) or phi(n) % 10 == 0",
    "confidence": 0.8,
    "is_terminal": false,
    "truth": true,
    "truth_reason": "holds"
  },
  {
    "node_id": 27,
    "parents": [
      26
    ],
    "claim": "For all integers n > 2, if n is a product of 11 and 3, then phi(n) is a multiple of 10 but not 20.",
    "predicate": "n <= 2 or not (tau(n) == 4 and 11 in [p for p in range(2, n) if is_prime(p) and n % p == 0] and 3 in [p for p in range(2, n) if is_prime(p) and n % p == 0]) or phi(n) % 10 == 0 and phi(n) % 20 != 0",
    "confidence": 0.7,
    "is_terminal": false,
    "truth": false,
    "truth_reason": "counterexample"
  }
]