[
  {
    "node_id": 0,
    "parents": [],
    "claim": "For all integers n, n^2 + n is even.",
    "predicate": "(n**2 + n) % 2 == 0",
    "confidence": 1.0,
    "is_terminal": false,
    "truth": true,
    "truth_reason": "holds"
  },
  {
    "node_id": 1,
    "parents": [
      0
    ],
    "claim": "For all integers n, n^2 + n is divisible by 2.",
    "predicate": "(n**2 + n) % 2 == 0",
    "confidence": 1.0,
    "is_terminal": false,
    "truth": true,
    "truth_reason": "holds"
  },
  {
    "node_id": 2,
    "parents": [
      0
    ],
    "claim": "For all integers n, n^3 + n is even.",
    "predicate": "(n**3 + n) % 2 == 0",
    "confidence": 0.9,
    "is_terminal": false,
    "truth": true,
    "truth_reason": "holds"
  },
  {
    "node_id": 3,
    "parents": [
      0
    ],
    "claim": "For all integers n, n^5 + n is even.",
    "predicate": "(n**5 + n) % 2 == 0",
    "confidence": 0.9,
    "is_terminal": false,
    "truth": true,
    "truth_reason": "holds"
  },
  {
    "node_id": 4,
    "parents": [
      0
    ],
    "claim": "For all integers n, n^7 + n is even.",
    "predicate": "(n**7 + n) % 2 == 0",
    "confidence": 0.9,
    "is_terminal": false,
    "truth": true,
    "truth_reason": "holds"
  },
  {
    "node_id": 5,
    "parents": [
      0
    ],
    "claim": "For all integers n, n^11 + n is even.",
    "predicate": "(n**11 + n) % 2 == 0",
    "confidence": 0.9,
    "is_terminal": false,
    "truth": true,
    "truth_reason": "holds"
  },
  {
    "node_id": 6,
    "parents": [
      0
    ],
    "claim": "For all integers n, n is even or n^2 + n is divisible by 4.",
    "predicate": "(n % 2 == 0) or ((n**2 + n) % 4 == 0)",
    "confidence": 0.95,
    "is_terminal": false,
    "truth": false,
    "truth_reason": "counterexample"
  },
  {
    "node_id": 7,
    "parents": [
      0
    ],
    "claim": "For all integers n, if n is prime, then n^2 + n is divisible by 6.",
    "predicate": "(not is_prime(n)) or ((n**2 + n) % 6 == 0)",
    "confidence": 0.8,
    "is_terminal": false,
    "truth": false,
    "truth_reason": "counterexample"
  },
  {
    "node_id": 8,
    "parents": [
      0
    ],
    "claim": "For all integers n, n^2 + n is divisible by gcd(n, n+1).",
    "predicate": "(n**2 + n) % gcd(n, n+1) == 0",
    "confidence": 0.95,
    "is_terminal": false,
    "truth": true,
    "truth_reason": "holds"
  },
  {
    "node_id": 9,
    "parents": [
      0
    ],
    "claim": "For all integers n, phi(n) divides n^2 + n if n is prime.",
    "predicate": "(not is_prime(n)) or (phi(n) != 0 and (n**2 + n) % phi(n) == 0)",
    "confidence": 0.7,
    "is_terminal": false,
    "truth": false,
    "truth_reason": "counterexample"
  },
  {
    "node_id": 10,
    "parents": [
      0
    ],
    "claim": "For all integers n, tau(n) divides n^2 + n if n is a perfect square.",
    "predicate": "(int(n**0.5)**2 != n) or (tau(n) != 0 and (n**2 + n) % tau(n) == 0)",
    "confidence": 0.6,
    "is_terminal": false,
    "truth": null,
    "truth_reason": "runtime:TypeError"
  },
  {
    "node_id": 11,
    "parents": [
      0
    ],
    "claim": "For all integers n, sigma(n) divides n^2 + n if n is a power of 2.",
    "predicate": "(math.log2(n) % 1 != 0) or (sigma(n) != 0 and (n**2 + n) % sigma(n) == 0)",
    "confidence": 0.55,
    "is_terminal": false,
    "truth": null,
    "truth_reason": "runtime:TypeError"
  },
  {
    "node_id": 12,
    "parents": [
      0
    ],
    "claim": "For all integers n, n^2 + n is congruent to 0 mod 3 if n is a multiple of 3.",
    "predicate": "(n % 3 != 0) or ((n**2 + n) % 3 == 0)",
    "confidence": 0.9,
    "is_terminal": false,
    "truth": true,
    "truth_reason": "holds"
  },
  {
    "node_id": 13,
    "parents": [
      0
    ],
    "claim": "For all integers n, n^2 + n is congruent to 0 mod 5 if n is a multiple of 5.",
    "predicate": "(n % 5 != 0) or ((n**2 + n) % 5 == 0)",
    "confidence": 0.85,
    "is_terminal": false,
    "truth": true,
    "truth_reason": "holds"
  },
  {
    "node_id": 14,
    "parents": [
      0
    ],
    "claim": "For all integers n, n^2 + n is congruent to 0 mod 7 if n is a multiple of 7.",
    "predicate": "(n % 7 != 0) or ((n**2 + n) % 7 == 0)",
    "confidence": 0.8,
    "is_terminal": false,
    "truth": true,
    "truth_reason": "holds"
  },
  {
    "node_id": 15,
    "parents": [
      0
    ],
    "claim": "For all integers n, the sum of the divisors of n^2 + n is even.",
    "predicate": "sigma(n**2 + n) % 2 == 0",
    "confidence": 0.7,
    "is_terminal": false,
    "truth": false,
    "truth_reason": "counterexample"
  },
  {
    "node_id": 16,
    "parents": [
      0
    ],
    "claim": "For all integers n, the product of the divisors of n^2 + n is a perfect square.",
    "predicate": "round(sigma(n**2 + n)**0.5) ** 2 == sigma(n**2 + n)",
    "confidence": 0.5,
    "is_terminal": false,
    "truth": false,
    "truth_reason": "counterexample"
  },
  {
    "node_id": 17,
    "parents": [
      0
    ],
    "claim": "For all integers n, if n is a perfect square, then n^2 + n is a perfect cube.",
    "predicate": "(int(n**0.5)**2 != n) or (round((n**2 + n)**(1/3)) ** 3 == n**2 + n)",
    "confidence": 0.4,
    "is_terminal": false,
    "truth": null,
    "truth_reason": "runtime:TypeError"
  },
  {
    "node_id": 18,
    "parents": [
      0
    ],
    "claim": "For all integers n, the number of divisors of n^2 + n is a power of 2.",
    "predicate": "math.log2(tau(n**2 + n)) % 1 == 0",
    "confidence": 0.45,
    "is_terminal": false,
    "truth": null,
    "truth_reason": "runtime:TypeError"
  },
  {
    "node_id": 19,
    "parents": [
      0
    ],
    "claim": "For all integers n, if n is a power of 2, then n^2 + n is a power of 2.",
    "predicate": "(math.log2(n) % 1 != 0) or (math.log2(n**2 + n) % 1 == 0)",
    "confidence": 0.5,
    "is_terminal": false,
    "truth": null,
    "truth_reason": "runtime:TypeError"
  },
  {
    "node_id": 20,
    "parents": [
      0
    ],
    "claim": "For all integers n, if n is prime, then n^2 + n is not a perfect square.",
    "predicate": "(not is_prime(n)) or (int((n**2 + n)**0.5)**2 != n**2 + n)",
    "confidence": 0.8,
    "is_terminal": false,
    "truth": true,
    "truth_reason": "holds"
  },
  {
    "node_id": 21,
    "parents": [
      0
    ],
    "claim": "For all integers n, if n is composite, then n^2 + n is not a prime power.",
    "predicate": "(is_prime(n)) or (not (math.log2(n**2 + n) % 1 == 0 or math.log(n**2 + n, 3) % 1 == 0 or math.log(n**2 + n, 5) % 1 == 0))",
    "confidence": 0.6,
    "is_terminal": false,
    "truth": null,
    "truth_reason": "runtime:TypeError"
  },
  {
    "node_id": 22,
    "parents": [
      0
    ],
    "claim": "For all integers n, n^2 + n has at least two distinct prime divisors if n is not a prime power.",
    "predicate": "(math.log2(n) % 1 == 0 or math.log(n, 3) % 1 == 0 or math.log(n, 5) % 1 == 0) or (len(set([p for p in range(2, int(n**0.5) + 1) if (n**2 + n) % p == 0])) > 1)",
    "confidence": 0.55,
    "is_terminal": false,
    "truth": null,
    "truth_reason": "runtime:TypeError"
  },
  {
    "node_id": 23,
    "parents": [
      0
    ],
    "claim": "For all integers n, n^2 + n is not a Carmichael number if n is not a prime power.",
    "predicate": "(math.log2(n) % 1 == 0 or math.log(n, 3) % 1 == 0 or math.log(n, 5) % 1 == 0) or (not (all((n**2 + n)**k % (n**2 + n) == pow(k, len(str(n**2 + n)), n**2 + n) for k in range(1, n**2 + n)) and not is_prime(n**2 + n)))",
    "confidence": 0.4,
    "is_terminal": false,
    "truth": null,
    "truth_reason": "runtime:TypeError"
  },
  {
    "node_id": 24,
    "parents": [
      0
    ],
    "claim": "For all integers n, n^2 + n has a divisor d such that d and n^2 + n/d are both perfect squares.",
    "predicate": "any((int((n**2 + n)/d)**2 == (n**2 + n)/d and int(d**0.5)**2 == d) for d in range(1, int((n**2 + n)**0.5) + 1) if (n**2 + n) % d == 0)",
    "confidence": 0.45,
    "is_terminal": false,
    "truth": false,
    "truth_reason": "counterexample"
  },
  {
    "node_id": 25,
    "parents": [
      0
    ],
    "claim": "For all integers n, if n is not a prime power, then n^2 + n has at least three distinct prime divisors.",
    "predicate": "(math.log2(n) % 1 == 0 or math.log(n, 3) % 1 == 0 or math.log(n, 5) % 1 == 0) or (len(set([p for p in range(2, int(n**0.5) + 1) if (n**2 + n) % p == 0])) > 2)",
    "confidence": 0.5,
    "is_terminal": false,
    "truth": null,
    "truth_reason": "runtime:TypeError"
  },
  {
    "node_id": 26,
    "parents": [
      0
    ],
    "claim": "For all integers n, if n is a prime power, then n^2 + n is a power of 2 or 3.",
    "predicate": "(not (math.log2(n) % 1 == 0 or math.log(n, 3) % 1 == 0 or math.log(n, 5) % 1 == 0)) or (math.log2(n**2 + n) % 1 == 0 or math.log(n**2 + n, 3) % 1 == 0)",
    "confidence": 0.4,
    "is_terminal": false,
    "truth": null,
    "truth_reason": "runtime:TypeError"
  },
  {
    "node_id": 27,
    "parents": [
      0
    ],
    "claim": "For all integers n, if n is not a perfect square, then n^2 + n is not a perfect cube.",
    "predicate": "(int(n**0.5)**2 == n) or (round((n**2 + n)**(1/3)) ** 3 != n**2 + n)",
    "confidence": 0.6,
    "is_terminal": false,
    "truth": null,
    "truth_reason": "runtime:TypeError"
  },
  {
    "node_id": 28,
    "parents": [
      0
    ],
    "claim": "For all integers n, n^2 + n has at least one prime divisor p such that p^2 divides n^2 + n.",
    "predicate": "any((n**2 + n) % (p**2) == 0 for p in range(2, int(n**0.5) + 1) if (n**2 + n) % p == 0)",
    "confidence": 0.5,
    "is_terminal": false,
    "truth": null,
    "truth_reason": "runtime:TypeError"
  },
  {
    "node_id": 29,
    "parents": [
      0
    ],
    "claim": "For all integers n, if n is a prime power, then n^2 + n has a prime divisor p such that p is a primitive root modulo n.",
    "predicate": "(not (math.log2(n) % 1 == 0 or math.log(n, 3) % 1 == 0 or math.log(n, 5) % 1 == 0)) or (any(pow(p, (n-1)//2, n) == n-1 for p in range(2, int(n**0.5) + 1) if (n**2 + n) % p == 0))",
    "confidence": 0.4,
    "is_terminal": false,
    "truth": null,
    "truth_reason": "runtime:TypeError"
  },
  {
    "node_id": 30,
    "parents": [
      0
    ],
    "claim": "For all integers n, if n is not a prime power, then n^2 + n has at least two distinct prime divisors p, q such that p and q are both primitive roots modulo n.",
    "predicate": "(math.log2(n) % 1 == 0 or math.log(n, 3) % 1 == 0 or math.log(n, 5) % 1 == 0) or (len(set([p for p in range(2, int(n**0.5) + 1) if (n**2 + n) % p == 0 and pow(p, (n-1)//2, n) == n-1])) > 1)",
    "confidence": 0.45,
    "is_terminal": false,
    "truth": null,
    "truth_reason": "runtime:TypeError"
  },
  {
    "node_id": 31,
    "parents": [
      0
    ],
    "claim": "For all integers n, if n is a perfect square, then n^2 + n has a divisor d such that d is a perfect square and n^2 + n/d is also a perfect square.",
    "predicate": "(int(n**0.5)**2 != n) or (any((int((n**2 + n)/d)**2 == (n**2 + n)/d and int(d**0.5)**2 == d) for d in range(1, int((n**2 + n)**0.5) + 1) if (n**2 + n) % d == 0))",
    "confidence": 0.5,
    "is_terminal": false,
    "truth": null,
    "truth_reason": "runtime:TypeError"
  },
  {
    "node_id": 32,
    "parents": [
      0
    ],
    "claim": "For all integers n, if n is not a prime power, then n^2 + n has at least three distinct prime divisors p, q, r such that p, q, and r are all primitive roots modulo n.",
    "predicate": "(math.log2(n) % 1 == 0 or math.log(n, 3) % 1 == 0 or math.log(n, 5) % 1 == 0) or (len(set([p for p in range(2, int(n**0.5) + 1) if (n**2 + n) % p == 0 and pow(p, (n-1)//2, n) == n-1])) > 2)",
    "confidence": 0.4,
    "is_terminal": false,
    "truth": null,
    "truth_reason": "runtime:TypeError"
  },
  {
    "node_id": 33,
    "parents": [
      0
    ],
    "claim": "For all integers n, n^2 + n has a prime divisor p such that p^2 divides n^2 + n and p is a primitive root modulo n.",
    "predicate": "any((n**2 + n) % (p**2) == 0 and pow(p, (n-1)//2, n) == n-1 for p in range(2, int(n**0.5) + 1) if (n**2 + n) % p == 0)",
    "confidence": 0.45,
    "is_terminal": false,
    "truth": null,
    "truth_reason": "runtime:TypeError"
  }
]